[{"qid": "Q45782", "label": "aquarium", "desc": "transparent tank of water for fish and water-dwelling species", "part": [{"pid": "Q1756633", "plabel": "aquatic animal"}, {"pid": "Q283", "plabel": "water"}, {"pid": "Q472273", "plabel": "aquarium plant"}, {"pid": "Q7632154", "plabel": "aquarium substrate"}]},
{"qid": "Q21209339", "label": "inositol oxygenase activity", "desc": "Catalysis of the reaction: myo-inositol + O(2) = D-glucuronate + H(2)O + H(+).", "part": [{"pid": "Q27125989", "plabel": "D-glucopyranuronate"}, {"pid": "Q283", "plabel": "water"}, {"pid": "Q3331426", "plabel": "myo-inositol"}, {"pid": "Q506710", "plabel": "hydron"}, {"pid": "Q5203615", "plabel": "dioxygen"}]},
{
    "qid": "Q8052",
    "label": "10th century",
    "desc": "century",
    "part": [
        {
            "pid": "Q276002",
            "plabel": "900s"
        },
        {
            "pid": "Q276443",
            "plabel": "910s"
        },
        {
            "pid": "Q79796",
            "plabel": "930s"
        },
        {
            "pid": "Q80747",
            "plabel": "960s"
        },
        {
            "pid": "Q80754",
            "plabel": "990s"
        },
        {
            "pid": "Q81113",
            "plabel": "950s"
        },
        {
            "pid": "Q81670",
            "plabel": "970s"
        },
        {
            "pid": "Q82254",
            "plabel": "920s"
        },
        {
            "pid": "Q82283",
            "plabel": "980s"
        },
        {
            "pid": "Q83049",
            "plabel": "940s"
        }
    ]
},

{
    "qid": "Q2336077",
    "label": "kidney development",
    "desc": "process whose specific outcome is the progression of the kidney over time, from its formation to the mature structure",
    "part": [
        {
            "pid": "Q1468875",
            "plabel": "mesonephros"
        },
        {
            "pid": "Q2366267",
            "plabel": "metanephros"
        },
        {
            "pid": "Q2656768",
            "plabel": "pronephros"
        },
        {
            "pid": "Q60745146",
            "plabel": "archinephros"
        }
    ]
},

{
    "qid": "Q18618696",
    "label": "boat noodles",
    "desc": "Thai noodle dish",
    "part": [
        {
            "pid": "Q1322949",
            "plabel": "rice noodle"
        },
        {
            "pid": "Q2901605",
            "plabel": "fermented bean curd"
        },
        {
            "pid": "Q8484030",
            "plabel": "dark soy sauce"
        }
    ]
},
{
    "qid": "Q76753469",
    "label": "protests of 2019",
    "desc": "global wave of popular street protests in 2019",
    "part": [
        {
            "pid": "Q58805164",
            "plabel": "yellow vests movement"
        },
        {
            "pid": "Q60289711",
            "plabel": "Sudanese Revolution"
        },
        {
            "pid": "Q64509602",
            "plabel": "2019–2020 Hong Kong protests"
        },
        {
            "pid": "Q65084224",
            "plabel": "Second Arab Spring"
        },
        {
            "pid": "Q68664291",
            "plabel": "September 2019 Indonesian protests and riots"
        },
        {
            "pid": "Q70580730",
            "plabel": "2019–2020 Catalan protests"
        },
        {
            "pid": "Q75161062",
            "plabel": "2019–20 Iranian protests"
        },
        {
            "pid": "Q75852493",
            "plabel": "2019 Latin American protests"
        },
        {
            "pid": "Q78455589",
            "plabel": "Citizenship (Amendment) Act protests"
        }
    ]
},
{
    "qid": "Q44127",
    "label": "server",
    "desc": "computer program or device that provides access to a central resource or other functionality for clients",
    "part": [
        {
            "pid": "Q1371279",
            "plabel": "server software"
        },
        {
            "pid": "Q64729893",
            "plabel": "server computer"
        }
    ]
}
]